.coveragerc
.gitattributes
.gitignore
.gitlab-ci.yml
.mailmap
AUTHORS.rst
CITING.rst
CONTRIBUTE.rst
INSTALL.rst
LICENSE.rst
MANIFEST.in
README.rst
README_WINDOWS.txt
RELEASE.rst
check_whitespace
conftest.py
kwant_red.jscm
pytest.ini
setup.cfg
setup.py
.gitlab/issue_templates/release.md
doc/Makefile
doc/source/conf.py
doc/source/index.rst
doc/source/_static/kwant_logo.png
doc/source/_static/mathconf.js
doc/source/_static/sidebar.js
doc/source/_static/togglediv.js
doc/source/figure/ab_ring_sketch.svg
doc/source/figure/ab_ring_sketch2.svg
doc/source/figure/superconductor_transport_sketch.svg
doc/source/pre/about.rst
doc/source/pre/authors.rst
doc/source/pre/citing.rst
doc/source/pre/contribute.rst
doc/source/pre/index.rst
doc/source/pre/install.rst
doc/source/pre/license.rst
doc/source/pre/whatsnew/0.2.rst
doc/source/pre/whatsnew/1.0.rst
doc/source/pre/whatsnew/1.1.rst
doc/source/pre/whatsnew/1.2.rst
doc/source/pre/whatsnew/1.3.rst
doc/source/pre/whatsnew/1.4.rst
doc/source/pre/whatsnew/1.5.rst
doc/source/pre/whatsnew/index.rst
doc/source/reference/index.rst
doc/source/reference/kwant.builder.rst
doc/source/reference/kwant.continuum.rst
doc/source/reference/kwant.digest.rst
doc/source/reference/kwant.graph.rst
doc/source/reference/kwant.kpm.rst
doc/source/reference/kwant.lattice.rst
doc/source/reference/kwant.linalg.rst
doc/source/reference/kwant.operator.rst
doc/source/reference/kwant.physics.rst
doc/source/reference/kwant.plotter.rst
doc/source/reference/kwant.qsymm.rst
doc/source/reference/kwant.rmt.rst
doc/source/reference/kwant.rst
doc/source/reference/kwant.solvers.mumps.rst
doc/source/reference/kwant.solvers.rst
doc/source/reference/kwant.solvers.sparse.rst
doc/source/reference/kwant.system.rst
doc/source/reference/kwant.wraparound.rst
doc/source/tutorial/boilerplate.py
doc/source/tutorial/discretize.rst
doc/source/tutorial/faq.rst
doc/source/tutorial/first_steps.rst
doc/source/tutorial/graphene.rst
doc/source/tutorial/index.rst
kwant.egg-info/PKG-INFO
kwant.egg-info/SOURCES.txt
kwant.egg-info/dependency_links.txt
kwant.egg-info/requires.txt
kwant.egg-info/top_level.txt
