Metadata-Version: 2.1
Name: kwant
Version: 1.5.0
Summary: Kwant: a package for quantum transport calculations
Home-page: https://kwant-project.org
Author: C. W. Groth (CEA), M. Wimmer, A. R. Akhmerov, X. Waintal (CEA), and others
Author-email: authors@kwant-project.org
License: BSD-2-Clause
Platform: Unix
Platform: Linux
Platform: MacOS X
Platform: Windows
Classifier: Development Status :: 5 - Production/Stable
Classifier: Intended Audience :: Science/Research
Classifier: Intended Audience :: Developers
Classifier: Programming Language :: Python :: 3 :: Only
Classifier: License :: OSI Approved :: BSD License
Classifier: Topic :: Software Development
Classifier: Topic :: Scientific/Engineering
Classifier: Operating System :: POSIX
Classifier: Operating System :: Unix
Classifier: Operating System :: MacOS :: MacOS X
Classifier: Operating System :: Microsoft :: Windows
Requires-Python: >=3.8
License-File: LICENSE.rst
Requires-Dist: numpy>=1.18.0
Requires-Dist: scipy!=1.6.1,>=1.3.0
Requires-Dist: tinyarray>=1.2.2
Provides-Extra: plotting
Requires-Dist: matplotlib>=3.2.2; extra == "plotting"
Requires-Dist: plotly>=2.7.0; extra == "plotting"
Provides-Extra: continuum
Requires-Dist: sympy>=1.5.1; extra == "continuum"
Provides-Extra: qsymm
Requires-Dist: qsymm>=1.2.6; extra == "qsymm"
Provides-Extra: mumps
Requires-Dist: python-mumps<0.1; extra == "mumps"
